certbotool/__init__.py
certbotool/cli/__init__.py
certbotool/cli/cli.py
certbotool/core/__init__.py
certbotool/core/executable.py
certbotool/core/rest.py
certbotool/core/userconf.py
certbotool/crond/__init__.py
certbotool/crond/crond.py
certbotool/dns/__init__.py
certbotool/dns/aliyun.py
certbotool/dns/dns.py
certbotool/dns/dnspod.py
etc/certbotool/daemon.json
etc/certbotool/conf.d/aliyun.json.template
etc/certbotool/conf.d/dnspod.json.template
usr/lib/systemd/system/certbotool-crond.service
certbotool-1.0.0.dist-info/METADATA
certbotool-1.0.0.dist-info/WHEEL
certbotool-1.0.0.dist-info/entry_points.txt
certbotool-1.0.0.dist-info/top_level.txt
certbotool-1.0.0.dist-info/RECORD
