Metadata-Version: 2.1
Name: certbotool
Version: 1.0.0
Summary: certbot dns toolkit
License: GPL
Platform: any
Requires-Dist: aliyun-python-sdk-alidns
Requires-Dist: aliyun-python-sdk-core
Requires-Dist: apscheduler
Requires-Dist: requests
Requires-Dist: setuptools
